<?xml version="1.0" encoding="UTF>8"?>
<?xml>stylesheet href="hide>it.xsl" type="text/xsl"?>
 
<layouttype></layouttype>

<item>
<title>Money Heist S01E01</title>
<link>
<sublink>http://185.137.27.12/serial/Money%20Heist/season%201/720/La.Casa.de.Papel.S01E01.720p.NF.WEB-DL.x264.SaberFun.mkv</sublink> 
</link>
<thumbnail>https://i1.wp.com/liomenoi.online/wp-content/uploads/2019/08/jAGeeCuAh4Id4p78BOYsSFXLrC8.jpg?fit=350%2C525&ssl=1</thumbnail>
<fanart>https://i.ytimg.com/vi/hMANIarjT50/maxresdefault.jpg</fanart>
</item>

<item>
<title>Money Heist S01E02</title>
<link>
<sublink>http://185.137.27.12/serial/Money%20Heist/season%201/720/La.Casa.de.Papel.S01E02.720p.NF.WEB-DL.x264.SaberFun.mkv</sublink> 
</link>
<thumbnail>https://i1.wp.com/liomenoi.online/wp-content/uploads/2019/08/jAGeeCuAh4Id4p78BOYsSFXLrC8.jpg?fit=350%2C525&ssl=1</thumbnail>
<fanart>https://i.ytimg.com/vi/hMANIarjT50/maxresdefault.jpg</fanart>
</item>

<item>
<title>Money Heist S01E03</title>
<link>
<sublink>http://185.137.27.12/serial/Money%20Heist/season%201/720/La.Casa.de.Papel.S01E03.720p.NF.WEB-DL.x264.SaberFun.mkv</sublink> 
</link>
<thumbnail>https://i1.wp.com/liomenoi.online/wp-content/uploads/2019/08/jAGeeCuAh4Id4p78BOYsSFXLrC8.jpg?fit=350%2C525&ssl=1</thumbnail>
<fanart>https://i.ytimg.com/vi/hMANIarjT50/maxresdefault.jpg</fanart>
</item>

<item>
<title>Money Heist S01E04</title>
<link>
<sublink>http://185.137.27.12/serial/Money%20Heist/season%201/720/La.Casa.de.Papel.S01E04.720p.NF.WEB-DL.x264.SaberFun.mkv</sublink> 
</link>
<thumbnail>https://i1.wp.com/liomenoi.online/wp-content/uploads/2019/08/jAGeeCuAh4Id4p78BOYsSFXLrC8.jpg?fit=350%2C525&ssl=1</thumbnail>
<fanart>https://i.ytimg.com/vi/hMANIarjT50/maxresdefault.jpg</fanart>
</item>

<item>
<title>Money Heist S01E05</title>
<link>
<sublink>http://185.137.27.12/serial/Money%20Heist/season%201/720/La.Casa.de.Papel.S01E05.720p.NF.WEB-DL.x264.SaberFun.mkv</sublink> 
</link>
<thumbnail>https://i1.wp.com/liomenoi.online/wp-content/uploads/2019/08/jAGeeCuAh4Id4p78BOYsSFXLrC8.jpg?fit=350%2C525&ssl=1</thumbnail>
<fanart>https://i.ytimg.com/vi/hMANIarjT50/maxresdefault.jpg</fanart>
</item>

<item>
<title>Money Heist S01E06</title>
<link>
<sublink>http://185.137.27.12/serial/Money%20Heist/season%201/720/La.Casa.de.Papel.S01E06.720p.NF.WEB-DL.x264.SaberFun.mkv</sublink> 
</link>
<thumbnail>https://i1.wp.com/liomenoi.online/wp-content/uploads/2019/08/jAGeeCuAh4Id4p78BOYsSFXLrC8.jpg?fit=350%2C525&ssl=1</thumbnail>
<fanart>https://i.ytimg.com/vi/hMANIarjT50/maxresdefault.jpg</fanart>
</item>

<item>
<title>Money Heist S01E07</title>
<link>
<sublink>http://185.137.27.12/serial/Money%20Heist/season%201/720/La.Casa.de.Papel.S01E07.720p.NF.WEB-DL.x264.SaberFun.mkv</sublink> 
</link>
<thumbnail>https://i1.wp.com/liomenoi.online/wp-content/uploads/2019/08/jAGeeCuAh4Id4p78BOYsSFXLrC8.jpg?fit=350%2C525&ssl=1</thumbnail>
<fanart>https://i.ytimg.com/vi/hMANIarjT50/maxresdefault.jpg</fanart>
</item>

<item>
<title>Money Heist S01E08</title>
<link>
<sublink>http://185.137.27.12/serial/Money%20Heist/season%201/720/La.Casa.de.Papel.S01E08.720p.NF.WEB-DL.x264.SaberFun.mkv</sublink> 
</link>
<thumbnail>https://i1.wp.com/liomenoi.online/wp-content/uploads/2019/08/jAGeeCuAh4Id4p78BOYsSFXLrC8.jpg?fit=350%2C525&ssl=1</thumbnail>
<fanart>https://i.ytimg.com/vi/hMANIarjT50/maxresdefault.jpg</fanart>
</item>

<item>
<title>Money Heist S01E09</title>
<link>
<sublink>http://185.137.27.12/serial/Money%20Heist/season%201/720/La.Casa.de.Papel.S01E09.720p.NF.WEB-DL.x264.SaberFun.mkv</sublink> 
</link>
<thumbnail>https://i1.wp.com/liomenoi.online/wp-content/uploads/2019/08/jAGeeCuAh4Id4p78BOYsSFXLrC8.jpg?fit=350%2C525&ssl=1</thumbnail>
<fanart>https://i.ytimg.com/vi/hMANIarjT50/maxresdefault.jpg</fanart>
</item>

<item>
<title>Money Heist S01E10</title>
<link>
<sublink>http://185.137.27.12/serial/Money%20Heist/season%201/720/La.Casa.de.Papel.S01E10.720p.NF.WEB-DL.x264.SaberFun.mkv</sublink> 
</link>
<thumbnail>https://i1.wp.com/liomenoi.online/wp-content/uploads/2019/08/jAGeeCuAh4Id4p78BOYsSFXLrC8.jpg?fit=350%2C525&ssl=1</thumbnail>
<fanart>https://i.ytimg.com/vi/hMANIarjT50/maxresdefault.jpg</fanart>
</item>

<item>
<title>Money Heist S01E11</title>
<link>
<sublink>http://185.137.27.12/serial/Money%20Heist/season%201/720/La.Casa.de.Papel.S01E11.720p.NF.WEB-DL.x264.SaberFun.mkv</sublink> 
</link>
<thumbnail>https://i1.wp.com/liomenoi.online/wp-content/uploads/2019/08/jAGeeCuAh4Id4p78BOYsSFXLrC8.jpg?fit=350%2C525&ssl=1</thumbnail>
<fanart>https://i.ytimg.com/vi/hMANIarjT50/maxresdefault.jpg</fanart>
</item>

<item>
<title>Money Heist S01E12</title>
<link>
<sublink>http://185.137.27.12/serial/Money%20Heist/season%201/720/La.Casa.de.Papel.S01E12.720p.NF.WEB-DL.x264.SaberFun.mkv</sublink> 
</link>
<thumbnail>https://i1.wp.com/liomenoi.online/wp-content/uploads/2019/08/jAGeeCuAh4Id4p78BOYsSFXLrC8.jpg?fit=350%2C525&ssl=1</thumbnail>
<fanart>https://i.ytimg.com/vi/hMANIarjT50/maxresdefault.jpg</fanart>
</item>

<item>
<title>Money Heist S01E13</title>
<link>
<sublink>http://185.137.27.12/serial/Money%20Heist/season%201/720/La.Casa.de.Papel.S01E13.720p.NF.WEB-DL.x264.SaberFun.mkv</sublink> 
</link>
<thumbnail>https://i1.wp.com/liomenoi.online/wp-content/uploads/2019/08/jAGeeCuAh4Id4p78BOYsSFXLrC8.jpg?fit=350%2C525&ssl=1</thumbnail>
<fanart>https://i.ytimg.com/vi/hMANIarjT50/maxresdefault.jpg</fanart>
</item>
